simplepipreqs/__init__.py
simplepipreqs/simplepipreqs.py
simplepipreqs-0.0.3.dist-info/LICENSE.txt
simplepipreqs-0.0.3.dist-info/METADATA
simplepipreqs-0.0.3.dist-info/WHEEL
simplepipreqs-0.0.3.dist-info/entry_points.txt
simplepipreqs-0.0.3.dist-info/top_level.txt
simplepipreqs-0.0.3.dist-info/RECORD
