Metadata-Version: 2.1
Name: simplepipreqs
Version: 0.0.3
Summary: Python module to generate requirements.txt for a given project.
Home-page: https://github.com/Atharva-Gundawar/simplepipreqs
Author: Atharva Gundawar
Author-email: atharva.n.gundawar@gmail.com
License: MIT
Keywords: Requirments Requirments.txt Requirment.txt python Ipython ipynb py
Platform: UNKNOWN
Classifier: License :: OSI Approved :: MIT License
Classifier: Programming Language :: Python
Classifier: Programming Language :: Python :: 3
Classifier: Programming Language :: Python :: 3.6
Classifier: Programming Language :: Python :: Implementation :: CPython
Classifier: Programming Language :: Python :: Implementation :: PyPy
Classifier: Operating System :: OS Independent
Requires-Python: >=3.6.0
Requires-Dist: pathlib
Requires-Dist: yarg
Requires-Dist: requests
Requires-Dist: argparse
